{
    "periodo":"2015-2016",
    "tipo_educativo":"EDUCACI&#211;N B&#193;SICA",
    "nivel_educativo":"PREESCOLAR",
    "servicio_educativo":"PREESCOLAR GENERAL",
    "clave_entidad":"01",
    "entidad":"AGUASCALIENTES",
    "clave_mun_del":"001",
    "municipio":"AGUASCALIENTES",
    "clave_localidad":"0001",
    "localidad":"AGUASCALIENTES",
    "clave":"01DJN0083E",
    "turno":"MATUTINO",
    "ambito":"URBANA",
    "centro_educativo":"ALFONSO MARTINEZ DOMINGUEZ",
    "control":"P&#218;BLICO",
    "domicilio":"MARINA NACIONAL",
    "num_exterior":"403",
    "entre_calle":"RIO MORCINIQUE",
    "y_calle":"FELIX DE LA PAZ",
    "calle_posterior":"AVENIDA GENERAL IGNACIO ZARAGOZA",
    "codigo_postal":"20050",
    "lada":"01449",
    "telefono":"9187649",
    "e_mail":"&nbsp;",
    "total_de_personal":"10",
    "personal_mujeres":"8",
    "personal_hombres":"2",
    "total_de_docentes":"5",
    "docentes_mujeres":"5",
    "docentes_hombres":"0",
    "total_de_alumnos":"142",
    "alumnos_mujeres":"75",
    "alumnos_hombres":"67",
    "total_de_grupos":"5",
    "aulas_existentes":"5",
    "aulas_en_uso":"5",
    "laboratorios":"0",
    "talleres":"0",
    "computadoras_en_operacion":"6",
    "computadoras_en_operacion_con_internet":"6",
    "computadoras_en_operacion_uso_educativo":"4",
    "altitud_msnm":"1878",
    "longitud":"-102.297994",
    "latitud":"21.892555",
    "longitud_gms":"-102:17:52.778",
    "latitud_gms":"21:53:33.197"
}
