{
    "periodo":"2015-2016",
    "tipo_educativo":"EDUCACI&#211;N B&#193;SICA",
    "nivel_educativo":"SECUNDARIA",
    "servicio_educativo":"SECUNDARIA GENERAL",
    "clave_entidad":"02",
    "entidad":"BAJA CALIFORNIA",
    "clave_mun_del":"001",
    "municipio":"ENSENADA",
    "clave_localidad":"0060",
    "localidad":"CAMAL&#218;",
    "clave":"02EES0204H",
    "turno":"MATUTINO",
    "ambito":"URBANA",
    "centro_educativo":"SECUNDARIA GENERAL NUM. 105",
    "control":"P&#218;BLICO",
    "domicilio":"GENERAL EMILIANO ZAPATA",
    "num_exterior":"&nbsp;",
    "entre_calle":"TERCERA (IGNACIO ALLENDE)",
    "y_calle":"SEGUNDA Y/O AGUSTIN DE ITURBIDE",
    "calle_posterior":"NINGUNO",
    "codigo_postal":"22910",
    "lada":"&nbsp;",
    "telefono":"6161654195",
    "e_mail":"sec.105camalu@hotmail.com",
    "total_de_personal":"34",
    "personal_mujeres":"20",
    "personal_hombres":"14",
    "total_de_docentes":"20",
    "docentes_mujeres":"8",
    "docentes_hombres":"12",
    "total_de_alumnos":"568",
    "alumnos_mujeres":"284",
    "alumnos_hombres":"284",
    "total_de_grupos":"15",
    "aulas_existentes":"15",
    "aulas_en_uso":"15",
    "laboratorios":"0",
    "talleres":"0",
    "computadoras_en_operacion":"28",
    "computadoras_en_operacion_con_internet":"6",
    "computadoras_en_operacion_uso_educativo":"22",
    "altitud_msnm":"0030",
    "longitud":"-116.063814",
    "latitud":"30.839488",
    "longitud_gms":"-116:03:49.729",
    "latitud_gms":"30:50:22.156"
}
