{
    "periodo":"2015-2016",
    "tipo_educativo":"EDUCACI&#211;N B&#193;SICA",
    "nivel_educativo":"PRIMARIA",
    "servicio_educativo":"PRIMARIA GENERAL",
    "clave_entidad":"02",
    "entidad":"BAJA CALIFORNIA",
    "clave_mun_del":"002",
    "municipio":"MEXICALI",
    "clave_localidad":"0001",
    "localidad":"MEXICALI",
    "clave":"02PPR0040A",
    "turno":"MATUTINO",
    "ambito":"URBANA",
    "centro_educativo":"M. MONTESSORI",
    "control":"PRIVADO",
    "domicilio":"HEROICO COLEGIO MILITAR",
    "num_exterior":"2001",
    "entre_calle":"LAZARO CARDENAS",
    "y_calle":"HEROICO COLEGIO MILITAR",
    "calle_posterior":"NINGUNO",
    "codigo_postal":"21180",
    "lada":"&nbsp;",
    "telefono":"6865824466",
    "e_mail":"mmontmaol@yahoo.com",
    "total_de_personal":"23",
    "personal_mujeres":"19",
    "personal_hombres":"4",
    "total_de_docentes":"6",
    "docentes_mujeres":"6",
    "docentes_hombres":"0",
    "total_de_alumnos":"191",
    "alumnos_mujeres":"89",
    "alumnos_hombres":"102",
    "total_de_grupos":"10",
    "aulas_existentes":"12",
    "aulas_en_uso":"10",
    "laboratorios":"0",
    "talleres":"0",
    "computadoras_en_operacion":"26",
    "computadoras_en_operacion_con_internet":"26",
    "computadoras_en_operacion_uso_educativo":"18",
    "altitud_msnm":"0001",
    "longitud":"-115.505243",
    "latitud":"32.624927",
    "longitud_gms":"-115:30:18.874",
    "latitud_gms":"32:37:29.738"
}
