{
    "periodo":"2015-2016",
    "tipo_educativo":"EDUCACI&#211;N B&#193;SICA",
    "nivel_educativo":"PRIMARIA",
    "servicio_educativo":"PRIMARIA GENERAL",
    "clave_entidad":"02",
    "entidad":"BAJA CALIFORNIA",
    "clave_mun_del":"002",
    "municipio":"MEXICALI",
    "clave_localidad":"0001",
    "localidad":"MEXICALI",
    "clave":"02PPR0340Y",
    "turno":"MATUTINO",
    "ambito":"URBANA",
    "centro_educativo":"ISMAR",
    "control":"PRIVADO",
    "domicilio":"DE LAS AMERICAS",
    "num_exterior":"214",
    "entre_calle":"BUENOS AIRES",
    "y_calle":"CARACAS",
    "calle_posterior":"NINGUNO",
    "codigo_postal":"21200",
    "lada":"&nbsp;",
    "telefono":"6865681586",
    "e_mail":"colegioismar@hotmail.com",
    "total_de_personal":"12",
    "personal_mujeres":"8",
    "personal_hombres":"4",
    "total_de_docentes":"3",
    "docentes_mujeres":"0",
    "docentes_hombres":"3",
    "total_de_alumnos":"84",
    "alumnos_mujeres":"41",
    "alumnos_hombres":"43",
    "total_de_grupos":"6",
    "aulas_existentes":"6",
    "aulas_en_uso":"6",
    "laboratorios":"0",
    "talleres":"0",
    "computadoras_en_operacion":"24",
    "computadoras_en_operacion_con_internet":"5",
    "computadoras_en_operacion_uso_educativo":"20",
    "altitud_msnm":"0001",
    "longitud":"-115.447481",
    "latitud":"32.662573",
    "longitud_gms":"-115:26:50.931",
    "latitud_gms":"32:39:45.264"
}
