{
    "periodo":"&nbsp;",
    "tipo_educativo":"EDUCACI&#211;N MEDIA SUPERIOR",
    "nivel_educativo":"BACHILLERATO",
    "servicio_educativo":"BACHILLERATO GENERAL",
    "clave_entidad":"03",
    "entidad":"BAJA CALIFORNIA SUR",
    "clave_mun_del":"003",
    "municipio":"LA PAZ",
    "clave_localidad":"0001",
    "localidad":"LA PAZ",
    "clave":"03PBH0008H",
    "turno":"MATUTINO",
    "ambito":"URBANA",
    "centro_educativo":"INSTITUTO CORCORAN S C",
    "control":"PRIVADO",
    "domicilio":"&nbsp;",
    "num_exterior":"&nbsp;",
    "entre_calle":"&nbsp;",
    "y_calle":"&nbsp;",
    "calle_posterior":"&nbsp;",
    "codigo_postal":"&nbsp;",
    "lada":"&nbsp;",
    "telefono":"&nbsp;",
    "e_mail":"&nbsp;",
    "total_de_personal":"16",
    "personal_mujeres":"10",
    "personal_hombres":"6",
    "total_de_docentes":"11",
    "docentes_mujeres":"6",
    "docentes_hombres":"5",
    "total_de_alumnos":"45",
    "alumnos_mujeres":"21",
    "alumnos_hombres":"24",
    "total_de_grupos":"4",
    "aulas_existentes":"6",
    "aulas_en_uso":"4",
    "laboratorios":"1",
    "talleres":"1",
    "computadoras_en_operacion":"9",
    "computadoras_en_operacion_con_internet":"9",
    "computadoras_en_operacion_uso_educativo":"6",
    "altitud_msnm":"0027",
    "longitud":"-110.305484",
    "latitud":"24.155013",
    "longitud_gms":"-110:18:19.744",
    "latitud_gms":"24:09:18.048"
}
