{
    "periodo":"2015-2016",
    "tipo_educativo":"EDUCACI&#211;N B&#193;SICA",
    "nivel_educativo":"PREESCOLAR",
    "servicio_educativo":"PREESCOLAR GENERAL",
    "clave_entidad":"07",
    "entidad":"CHIAPAS",
    "clave_mun_del":"078",
    "municipio":"SAN CRIST&#211;BAL DE LAS CASAS",
    "clave_localidad":"0001",
    "localidad":"SAN CRIST&#211;BAL DE LAS CASAS",
    "clave":"07EJN0047T",
    "turno":"MATUTINO",
    "ambito":"URBANA",
    "centro_educativo":"ROSARIO CASTELLANOS FIGUEROA",
    "control":"P&#218;BLICO",
    "domicilio":"CALLE ITALIA",
    "num_exterior":"3",
    "entre_calle":"FILIBERTO FLORES",
    "y_calle":"ROSARIO CASTELLANOS",
    "calle_posterior":"NINGUNO",
    "codigo_postal":"29200",
    "lada":"01967",
    "telefono":"&nbsp;",
    "e_mail":"&nbsp;",
    "total_de_personal":"20",
    "personal_mujeres":"13",
    "personal_hombres":"7",
    "total_de_docentes":"9",
    "docentes_mujeres":"7",
    "docentes_hombres":"2",
    "total_de_alumnos":"296",
    "alumnos_mujeres":"153",
    "alumnos_hombres":"143",
    "total_de_grupos":"9",
    "aulas_existentes":"9",
    "aulas_en_uso":"9",
    "laboratorios":"0",
    "talleres":"0",
    "computadoras_en_operacion":"0",
    "computadoras_en_operacion_con_internet":"0",
    "computadoras_en_operacion_uso_educativo":"0",
    "altitud_msnm":"2121",
    "longitud":"-92.644524",
    "latitud":"16.751517",
    "longitud_gms":"-92:38:40.285",
    "latitud_gms":"16:45:05.462"
}
