{
    "periodo":"&nbsp;",
    "tipo_educativo":"EDUCACI&#211;N MEDIA SUPERIOR",
    "nivel_educativo":"BACHILLERATO",
    "servicio_educativo":"BACHILLERATO GENERAL",
    "clave_entidad":"07",
    "entidad":"CHIAPAS",
    "clave_mun_del":"103",
    "municipio":"TUZANT&#193;N",
    "clave_localidad":"0034",
    "localidad":"ESTACI&#211;N TUZANT&#193;N",
    "clave":"07EMS0105L",
    "turno":"MATUTINO",
    "ambito":"RURAL",
    "centro_educativo":"179ESTACI&#211;N TUZANTAN",
    "control":"P&#218;BLICO",
    "domicilio":"&nbsp;",
    "num_exterior":"&nbsp;",
    "entre_calle":"&nbsp;",
    "y_calle":"&nbsp;",
    "calle_posterior":"&nbsp;",
    "codigo_postal":"&nbsp;",
    "lada":"&nbsp;",
    "telefono":"&nbsp;",
    "e_mail":"&nbsp;",
    "total_de_personal":"9",
    "personal_mujeres":"5",
    "personal_hombres":"4",
    "total_de_docentes":"5",
    "docentes_mujeres":"3",
    "docentes_hombres":"2",
    "total_de_alumnos":"193",
    "alumnos_mujeres":"75",
    "alumnos_hombres":"118",
    "total_de_grupos":"6",
    "aulas_existentes":"6",
    "aulas_en_uso":"6",
    "laboratorios":"1",
    "talleres":"0",
    "computadoras_en_operacion":"25",
    "computadoras_en_operacion_con_internet":"0",
    "computadoras_en_operacion_uso_educativo":"23",
    "altitud_msnm":"0026",
    "longitud":"-92.451234",
    "latitud":"15.106577",
    "longitud_gms":"-92:27:04.442",
    "latitud_gms":"15:06:23.678"
}
