{
    "periodo":"2015-2016",
    "tipo_educativo":"EDUCACI&#211;N B&#193;SICA",
    "nivel_educativo":"PRIMARIA",
    "servicio_educativo":"PRIMARIA GENERAL",
    "clave_entidad":"08",
    "entidad":"CHIHUAHUA",
    "clave_mun_del":"036",
    "municipio":"JIM&#201;NEZ",
    "clave_localidad":"0147",
    "localidad":"TIERRA BLANCA",
    "clave":"08DPR0258N",
    "turno":"MATUTINO",
    "ambito":"RURAL",
    "centro_educativo":"24 DE FEBRERO",
    "control":"P&#218;BLICO",
    "domicilio":"A LA ORILLA DEL RANCHO SALIENDA A LA CARRETERA CUOTA JIMENEZ CAMA",
    "num_exterior":"&nbsp;",
    "entre_calle":"&nbsp;",
    "y_calle":"&nbsp;",
    "calle_posterior":"NINGUNO",
    "codigo_postal":"33987",
    "lada":"01629",
    "telefono":"5423984",
    "e_mail":"&nbsp;",
    "total_de_personal":"3",
    "personal_mujeres":"2",
    "personal_hombres":"1",
    "total_de_docentes":"2",
    "docentes_mujeres":"1",
    "docentes_hombres":"1",
    "total_de_alumnos":"32",
    "alumnos_mujeres":"18",
    "alumnos_hombres":"14",
    "total_de_grupos":"2",
    "aulas_existentes":"4",
    "aulas_en_uso":"2",
    "laboratorios":"0",
    "talleres":"0",
    "computadoras_en_operacion":"0",
    "computadoras_en_operacion_con_internet":"0",
    "computadoras_en_operacion_uso_educativo":"0",
    "altitud_msnm":"1371",
    "longitud":"-104.880278",
    "latitud":"27.183889",
    "longitud_gms":"-104:52:49.000",
    "latitud_gms":"27:11:02.000"
}
