{
    "periodo":"&nbsp;",
    "tipo_educativo":"EDUCACI&#211;N B&#193;SICA",
    "nivel_educativo":"PREESCOLAR",
    "servicio_educativo":"PREESCOLAR GENERAL",
    "clave_entidad":"08",
    "entidad":"CHIHUAHUA",
    "clave_mun_del":"037",
    "municipio":"JU&#193;REZ",
    "clave_localidad":"0001",
    "localidad":"JU&#193;REZ",
    "clave":"08PJN0485X",
    "turno":"MATUTINO",
    "ambito":"URBANA",
    "centro_educativo":"COLEGIO ANALIZ",
    "control":"PRIVADO",
    "domicilio":"BOULEVAR MANUEL GOMEZ MORIN",
    "num_exterior":"8812",
    "entre_calle":"CAMINO ESCUDERO",
    "y_calle":"PASEO DE LA VICTORIA",
    "calle_posterior":"NINGUNO",
    "codigo_postal":"32470",
    "lada":"&nbsp;",
    "telefono":"6566131734",
    "e_mail":"COLEGIO-ANA&#209;OZ@HOTMAIL.COM",
    "total_de_personal":"0",
    "personal_mujeres":"0",
    "personal_hombres":"0",
    "total_de_docentes":"0",
    "docentes_mujeres":"0",
    "docentes_hombres":"0",
    "total_de_alumnos":"0",
    "alumnos_mujeres":"0",
    "alumnos_hombres":"0",
    "total_de_grupos":"0",
    "aulas_existentes":"0",
    "aulas_en_uso":"0",
    "laboratorios":"0",
    "talleres":"0",
    "computadoras_en_operacion":"0",
    "computadoras_en_operacion_con_internet":"0",
    "computadoras_en_operacion_uso_educativo":"0",
    "altitud_msnm":"1131",
    "longitud":"-106.401634",
    "latitud":"31.703051",
    "longitud_gms":"-106:24:05.881",
    "latitud_gms":"31:42:10.984"
}
