{
    "periodo":"2015-2016",
    "tipo_educativo":"EDUCACI&#211;N B&#193;SICA",
    "nivel_educativo":"PREESCOLAR",
    "servicio_educativo":"PREESCOLAR GENERAL",
    "clave_entidad":"10",
    "entidad":"DURANGO",
    "clave_mun_del":"036",
    "municipio":"TLAHUALILO",
    "clave_localidad":"0015",
    "localidad":"CECEDA",
    "clave":"10DJN0510P",
    "turno":"MATUTINO",
    "ambito":"RURAL",
    "centro_educativo":"PROF. MOISES SAENZ",
    "control":"P&#218;BLICO",
    "domicilio":"NINGUNO",
    "num_exterior":"&nbsp;",
    "entre_calle":"16 DE SEPTIEMBRE",
    "y_calle":"NINGUNO",
    "calle_posterior":"NINGUNO",
    "codigo_postal":"35290",
    "lada":"&nbsp;",
    "telefono":"&nbsp;",
    "e_mail":"&nbsp;",
    "total_de_personal":"1",
    "personal_mujeres":"1",
    "personal_hombres":"0",
    "total_de_docentes":"1",
    "docentes_mujeres":"1",
    "docentes_hombres":"0",
    "total_de_alumnos":"11",
    "alumnos_mujeres":"7",
    "alumnos_hombres":"4",
    "total_de_grupos":"1",
    "aulas_existentes":"1",
    "aulas_en_uso":"1",
    "laboratorios":"0",
    "talleres":"0",
    "computadoras_en_operacion":"0",
    "computadoras_en_operacion_con_internet":"0",
    "computadoras_en_operacion_uso_educativo":"0",
    "altitud_msnm":"1093",
    "longitud":"-103.404478",
    "latitud":"26.070140",
    "longitud_gms":"-103:24:16.119",
    "latitud_gms":"26:04:12.505"
}
