{
    "periodo":"&nbsp;",
    "tipo_educativo":"EDUCACI&#211;N MEDIA SUPERIOR",
    "nivel_educativo":"BACHILLERATO",
    "servicio_educativo":"BACHILLERATO GENERAL",
    "clave_entidad":"10",
    "entidad":"DURANGO",
    "clave_mun_del":"005",
    "municipio":"DURANGO",
    "clave_localidad":"0001",
    "localidad":"VICTORIA DE DURANGO",
    "clave":"10PBH0081Z",
    "turno":"VESPERTINO",
    "ambito":"URBANA",
    "centro_educativo":"COLEGIO LIBERTADORES DE DURANGO",
    "control":"PRIVADO",
    "domicilio":"&nbsp;",
    "num_exterior":"&nbsp;",
    "entre_calle":"&nbsp;",
    "y_calle":"&nbsp;",
    "calle_posterior":"&nbsp;",
    "codigo_postal":"&nbsp;",
    "lada":"&nbsp;",
    "telefono":"&nbsp;",
    "e_mail":"&nbsp;",
    "total_de_personal":"13",
    "personal_mujeres":"6",
    "personal_hombres":"7",
    "total_de_docentes":"12",
    "docentes_mujeres":"5",
    "docentes_hombres":"7",
    "total_de_alumnos":"46",
    "alumnos_mujeres":"17",
    "alumnos_hombres":"29",
    "total_de_grupos":"3",
    "aulas_existentes":"1",
    "aulas_en_uso":"1",
    "laboratorios":"0",
    "talleres":"0",
    "computadoras_en_operacion":"19",
    "computadoras_en_operacion_con_internet":"19",
    "computadoras_en_operacion_uso_educativo":"10",
    "altitud_msnm":"1890",
    "longitud":"-104.675957",
    "latitud":"24.022503",
    "longitud_gms":"-104:40:33.444",
    "latitud_gms":"24:01:21.010"
}
