{
    "periodo":"2015-2016",
    "tipo_educativo":"EDUCACI&#211;N B&#193;SICA",
    "nivel_educativo":"PRIMARIA",
    "servicio_educativo":"PRIMARIA GENERAL",
    "clave_entidad":"11",
    "entidad":"GUANAJUATO",
    "clave_mun_del":"038",
    "municipio":"TARANDACUAO",
    "clave_localidad":"0010",
    "localidad":"PASO DE OVEJAS (EL PUENTE)",
    "clave":"11DPR0383Z",
    "turno":"MATUTINO",
    "ambito":"RURAL",
    "centro_educativo":"IGNACIO ALLENDE",
    "control":"P&#218;BLICO",
    "domicilio":"IGNACIO ALLENDE",
    "num_exterior":"&nbsp;",
    "entre_calle":"BENITO JUAREZ",
    "y_calle":"MIGUEL HIDALGO",
    "calle_posterior":"NINGUNO",
    "codigo_postal":"38790",
    "lada":"&nbsp;",
    "telefono":"&nbsp;",
    "e_mail":"&nbsp;",
    "total_de_personal":"2",
    "personal_mujeres":"1",
    "personal_hombres":"1",
    "total_de_docentes":"2",
    "docentes_mujeres":"1",
    "docentes_hombres":"1",
    "total_de_alumnos":"31",
    "alumnos_mujeres":"11",
    "alumnos_hombres":"20",
    "total_de_grupos":"6",
    "aulas_existentes":"3",
    "aulas_en_uso":"2",
    "laboratorios":"0",
    "talleres":"0",
    "computadoras_en_operacion":"0",
    "computadoras_en_operacion_con_internet":"0",
    "computadoras_en_operacion_uso_educativo":"0",
    "altitud_msnm":"1926",
    "longitud":"-100.510224",
    "latitud":"20.055578",
    "longitud_gms":"-100:30:36.805",
    "latitud_gms":"20:03:20.080"
}
