{
    "periodo":"2014-2015",
    "tipo_educativo":"CAPACITACI&#211;N P. TRABAJO",
    "nivel_educativo":"C. P/TRABAJO",
    "servicio_educativo":"FORMACI&#211;N P. TRABAJO",
    "clave_entidad":"11",
    "entidad":"GUANAJUATO",
    "clave_mun_del":"009",
    "municipio":"COMONFORT",
    "clave_localidad":"0001",
    "localidad":"COMONFORT",
    "clave":"11EIC0007J",
    "turno":"DISCONTINUO",
    "ambito":"URBANA",
    "centro_educativo":"IECA PLANTEL COMONFORT",
    "control":"P&#218;BLICO",
    "domicilio":"PROLONGACION FRANCISCO I. MADERO",
    "num_exterior":"SN",
    "entre_calle":"NO APLICA",
    "y_calle":"NO APLICA",
    "calle_posterior":"NINGUNO",
    "codigo_postal":"38210",
    "lada":"&nbsp;",
    "telefono":"014121562911",
    "e_mail":"iecacomonfort@guanajuato.gob.mx",
    "total_de_personal":"35",
    "personal_mujeres":"28",
    "personal_hombres":"7",
    "total_de_docentes":"2",
    "docentes_mujeres":"2",
    "docentes_hombres":"0",
    "total_de_alumnos":"2355",
    "alumnos_mujeres":"2090",
    "alumnos_hombres":"265",
    "total_de_grupos":"181",
    "aulas_existentes":"0",
    "aulas_en_uso":"0",
    "laboratorios":"0",
    "talleres":"0",
    "computadoras_en_operacion":"0",
    "computadoras_en_operacion_con_internet":"0",
    "computadoras_en_operacion_uso_educativo":"0",
    "altitud_msnm":"1787",
    "longitud":"-100.752680",
    "latitud":"20.721985",
    "longitud_gms":"-100:45:09.649",
    "latitud_gms":"20:43:19.145"
}
