{
    "periodo":"&nbsp;",
    "tipo_educativo":"EDUCACI&#211;N MEDIA SUPERIOR",
    "nivel_educativo":"BACHILLERATO",
    "servicio_educativo":"BACHILLERATO GENERAL",
    "clave_entidad":"11",
    "entidad":"GUANAJUATO",
    "clave_mun_del":"020",
    "municipio":"LE&#211;N",
    "clave_localidad":"0413",
    "localidad":"LOS RAM&#205;REZ",
    "clave":"11ETH0119E",
    "turno":"MATUTINO",
    "ambito":"RURAL",
    "centro_educativo":"VIDEOBACHILLERATO",
    "control":"P&#218;BLICO",
    "domicilio":"&nbsp;",
    "num_exterior":"&nbsp;",
    "entre_calle":"&nbsp;",
    "y_calle":"&nbsp;",
    "calle_posterior":"&nbsp;",
    "codigo_postal":"&nbsp;",
    "lada":"&nbsp;",
    "telefono":"&nbsp;",
    "e_mail":"&nbsp;",
    "total_de_personal":"4",
    "personal_mujeres":"1",
    "personal_hombres":"3",
    "total_de_docentes":"3",
    "docentes_mujeres":"1",
    "docentes_hombres":"2",
    "total_de_alumnos":"136",
    "alumnos_mujeres":"89",
    "alumnos_hombres":"47",
    "total_de_grupos":"3",
    "aulas_existentes":"3",
    "aulas_en_uso":"3",
    "laboratorios":"0",
    "talleres":"1",
    "computadoras_en_operacion":"35",
    "computadoras_en_operacion_con_internet":"35",
    "computadoras_en_operacion_uso_educativo":"35",
    "altitud_msnm":"1792",
    "longitud":"-101.646739",
    "latitud":"21.014175",
    "longitud_gms":"-101:38:48.259",
    "latitud_gms":"21:00:51.029"
}
