{
    "periodo":"&nbsp;",
    "tipo_educativo":"EDUCACI&#211;N MEDIA SUPERIOR",
    "nivel_educativo":"BACHILLERATO",
    "servicio_educativo":"BACHILLERATO GENERAL",
    "clave_entidad":"11",
    "entidad":"GUANAJUATO",
    "clave_mun_del":"021",
    "municipio":"MOROLE&#211;N",
    "clave_localidad":"0001",
    "localidad":"MOROLE&#211;N",
    "clave":"11PBH0278J",
    "turno":"MATUTINO",
    "ambito":"URBANA",
    "centro_educativo":"UNIVERSIDAD DE LEON PLANTEL MOROLEON",
    "control":"PRIVADO",
    "domicilio":"&nbsp;",
    "num_exterior":"&nbsp;",
    "entre_calle":"&nbsp;",
    "y_calle":"&nbsp;",
    "calle_posterior":"&nbsp;",
    "codigo_postal":"&nbsp;",
    "lada":"&nbsp;",
    "telefono":"&nbsp;",
    "e_mail":"&nbsp;",
    "total_de_personal":"22",
    "personal_mujeres":"11",
    "personal_hombres":"11",
    "total_de_docentes":"8",
    "docentes_mujeres":"4",
    "docentes_hombres":"4",
    "total_de_alumnos":"38",
    "alumnos_mujeres":"21",
    "alumnos_hombres":"17",
    "total_de_grupos":"3",
    "aulas_existentes":"47",
    "aulas_en_uso":"47",
    "laboratorios":"2",
    "talleres":"6",
    "computadoras_en_operacion":"53",
    "computadoras_en_operacion_con_internet":"53",
    "computadoras_en_operacion_uso_educativo":"46",
    "altitud_msnm":"1807",
    "longitud":"-101.184727",
    "latitud":"20.129905",
    "longitud_gms":"-101:11:05.017",
    "latitud_gms":"20:07:47.657"
}
