{
    "periodo":"2015-2016",
    "tipo_educativo":"EDUCACI&#211;N B&#193;SICA",
    "nivel_educativo":"PREESCOLAR",
    "servicio_educativo":"PREESCOLAR GENERAL",
    "clave_entidad":"12",
    "entidad":"GUERRERO",
    "clave_mun_del":"007",
    "municipio":"ARCELIA",
    "clave_localidad":"0067",
    "localidad":"TULATENGO",
    "clave":"12DJN0758E",
    "turno":"MATUTINO",
    "ambito":"RURAL",
    "centro_educativo":"PROCORO PORCAYO FLORES",
    "control":"P&#218;BLICO",
    "domicilio":"NINGUNO",
    "num_exterior":"&nbsp;",
    "entre_calle":"NINGUNO",
    "y_calle":"NINGUNO",
    "calle_posterior":"NINGUNO",
    "codigo_postal":"40500",
    "lada":"01732",
    "telefono":"&nbsp;",
    "e_mail":"&nbsp;",
    "total_de_personal":"1",
    "personal_mujeres":"1",
    "personal_hombres":"0",
    "total_de_docentes":"1",
    "docentes_mujeres":"1",
    "docentes_hombres":"0",
    "total_de_alumnos":"11",
    "alumnos_mujeres":"3",
    "alumnos_hombres":"8",
    "total_de_grupos":"1",
    "aulas_existentes":"2",
    "aulas_en_uso":"1",
    "laboratorios":"0",
    "talleres":"0",
    "computadoras_en_operacion":"0",
    "computadoras_en_operacion_con_internet":"0",
    "computadoras_en_operacion_uso_educativo":"0",
    "altitud_msnm":"0393",
    "longitud":"-100.298682",
    "latitud":"18.266377",
    "longitud_gms":"-100:17:55.255",
    "latitud_gms":"18:15:58.957"
}
