{
    "periodo":"2015-2016",
    "tipo_educativo":"EDUCACI&#211;N B&#193;SICA",
    "nivel_educativo":"PRIMARIA",
    "servicio_educativo":"PRIMARIA IND&#205;GENA",
    "clave_entidad":"12",
    "entidad":"GUERRERO",
    "clave_mun_del":"071",
    "municipio":"XOCHISTLAHUACA",
    "clave_localidad":"0006",
    "localidad":"GUADALUPE VICTORIA",
    "clave":"12DPB1193M",
    "turno":"MATUTINO",
    "ambito":"URBANA",
    "centro_educativo":"ESCUDO NACIONAL",
    "control":"P&#218;BLICO",
    "domicilio":"BENITO JUAREZ",
    "num_exterior":"&nbsp;",
    "entre_calle":"&nbsp;",
    "y_calle":"&nbsp;",
    "calle_posterior":"NINGUNO",
    "codigo_postal":"41770",
    "lada":"01741",
    "telefono":"&nbsp;",
    "e_mail":"&nbsp;",
    "total_de_personal":"15",
    "personal_mujeres":"5",
    "personal_hombres":"10",
    "total_de_docentes":"14",
    "docentes_mujeres":"5",
    "docentes_hombres":"9",
    "total_de_alumnos":"218",
    "alumnos_mujeres":"100",
    "alumnos_hombres":"118",
    "total_de_grupos":"14",
    "aulas_existentes":"13",
    "aulas_en_uso":"13",
    "laboratorios":"0",
    "talleres":"0",
    "computadoras_en_operacion":"0",
    "computadoras_en_operacion_con_internet":"0",
    "computadoras_en_operacion_uso_educativo":"0",
    "altitud_msnm":"0440",
    "longitud":"-98.180140",
    "latitud":"16.752743",
    "longitud_gms":"-98:10:48.505",
    "latitud_gms":"16:45:09.874"
}
