{
    "periodo":"2015-2016",
    "tipo_educativo":"EDUCACI&#211;N B&#193;SICA",
    "nivel_educativo":"PREESCOLAR",
    "servicio_educativo":"PREESCOLAR GENERAL",
    "clave_entidad":"13",
    "entidad":"HIDALGO",
    "clave_mun_del":"048",
    "municipio":"PACHUCA DE SOTO",
    "clave_localidad":"0001",
    "localidad":"PACHUCA DE SOTO",
    "clave":"13DJN0830X",
    "turno":"MATUTINO",
    "ambito":"URBANA",
    "centro_educativo":"LIC. JESUS REYES HEROLES",
    "control":"P&#218;BLICO",
    "domicilio":"SOLIDARIDAD",
    "num_exterior":"SN",
    "entre_calle":"AZOYATLA",
    "y_calle":"REFORMA",
    "calle_posterior":"NINGUNO",
    "codigo_postal":"42090",
    "lada":"01771",
    "telefono":"2119150",
    "e_mail":"jdnreyesheroles@hotmail.com, eunice_rage@hotmail.c",
    "total_de_personal":"5",
    "personal_mujeres":"5",
    "personal_hombres":"0",
    "total_de_docentes":"3",
    "docentes_mujeres":"3",
    "docentes_hombres":"0",
    "total_de_alumnos":"66",
    "alumnos_mujeres":"29",
    "alumnos_hombres":"37",
    "total_de_grupos":"3",
    "aulas_existentes":"5",
    "aulas_en_uso":"3",
    "laboratorios":"0",
    "talleres":"0",
    "computadoras_en_operacion":"0",
    "computadoras_en_operacion_con_internet":"0",
    "computadoras_en_operacion_uso_educativo":"0",
    "altitud_msnm":"2378",
    "longitud":"-98.737001",
    "latitud":"20.122360",
    "longitud_gms":"-98:44:13.202",
    "latitud_gms":"20:07:20.495"
}
