{
    "periodo":"2015-2016",
    "tipo_educativo":"EDUCACI&#211;N B&#193;SICA",
    "nivel_educativo":"PREESCOLAR",
    "servicio_educativo":"PREESCOLAR GENERAL",
    "clave_entidad":"14",
    "entidad":"JALISCO",
    "clave_mun_del":"125",
    "municipio":"SAN IGNACIO CERRO GORDO",
    "clave_localidad":"0073",
    "localidad":"SAN NICOL&#193;S",
    "clave":"14DJN5554Q",
    "turno":"MATUTINO",
    "ambito":"RURAL",
    "centro_educativo":"JUAN ESCUTIA",
    "control":"P&#218;BLICO",
    "domicilio":"SAN NICOLAS",
    "num_exterior":"&nbsp;",
    "entre_calle":"NINGUNO",
    "y_calle":"FRANCISCO OROZCO",
    "calle_posterior":"NINGUNO",
    "codigo_postal":"47190",
    "lada":"&nbsp;",
    "telefono":"&nbsp;",
    "e_mail":"karyorozco10@hotmail.com",
    "total_de_personal":"1",
    "personal_mujeres":"1",
    "personal_hombres":"0",
    "total_de_docentes":"1",
    "docentes_mujeres":"1",
    "docentes_hombres":"0",
    "total_de_alumnos":"9",
    "alumnos_mujeres":"6",
    "alumnos_hombres":"3",
    "total_de_grupos":"1",
    "aulas_existentes":"1",
    "aulas_en_uso":"1",
    "laboratorios":"0",
    "talleres":"0",
    "computadoras_en_operacion":"0",
    "computadoras_en_operacion_con_internet":"0",
    "computadoras_en_operacion_uso_educativo":"0",
    "altitud_msnm":"2006",
    "longitud":"-102.497192",
    "latitud":"20.703569",
    "longitud_gms":"-102:29:49.892",
    "latitud_gms":"20:42:12.848"
}
