{
    "periodo":"&nbsp;",
    "tipo_educativo":"EDUCACI&#211;N MEDIA SUPERIOR",
    "nivel_educativo":"BACHILLERATO",
    "servicio_educativo":"BACHILLERATO T&#201;CNICO",
    "clave_entidad":"15",
    "entidad":"M&#201;XICO",
    "clave_mun_del":"007",
    "municipio":"AMANALCO",
    "clave_localidad":"0009",
    "localidad":"EL POTRERO",
    "clave":"15ECT0112M",
    "turno":"DISCONTINUO",
    "ambito":"RURAL",
    "centro_educativo":"CBT AMANALCO DE BECERRA",
    "control":"P&#218;BLICO",
    "domicilio":"&nbsp;",
    "num_exterior":"&nbsp;",
    "entre_calle":"&nbsp;",
    "y_calle":"&nbsp;",
    "calle_posterior":"&nbsp;",
    "codigo_postal":"&nbsp;",
    "lada":"&nbsp;",
    "telefono":"&nbsp;",
    "e_mail":"&nbsp;",
    "total_de_personal":"15",
    "personal_mujeres":"7",
    "personal_hombres":"8",
    "total_de_docentes":"10",
    "docentes_mujeres":"5",
    "docentes_hombres":"5",
    "total_de_alumnos":"78",
    "alumnos_mujeres":"39",
    "alumnos_hombres":"39",
    "total_de_grupos":"3",
    "aulas_existentes":"3",
    "aulas_en_uso":"3",
    "laboratorios":"1",
    "talleres":"0",
    "computadoras_en_operacion":"22",
    "computadoras_en_operacion_con_internet":"1",
    "computadoras_en_operacion_uso_educativo":"21",
    "altitud_msnm":"2671",
    "longitud":"-99.997239",
    "latitud":"19.305787",
    "longitud_gms":"-99:59:50.060",
    "latitud_gms":"19:18:20.834"
}
