{
    "periodo":"&nbsp;",
    "tipo_educativo":"EDUCACI&#211;N MEDIA SUPERIOR",
    "nivel_educativo":"BACHILLERATO",
    "servicio_educativo":"BACHILLERATO GENERAL",
    "clave_entidad":"16",
    "entidad":"MICHOAC&#193;N DE OCAMPO",
    "clave_mun_del":"026",
    "municipio":"CHINICUILA",
    "clave_localidad":"0048",
    "localidad":"SALITRE DE ESTOPILA",
    "clave":"16ETH0033U",
    "turno":"VESPERTINO",
    "ambito":"RURAL",
    "centro_educativo":"TELEBACHILLERATO NUM. 33",
    "control":"P&#218;BLICO",
    "domicilio":"&nbsp;",
    "num_exterior":"&nbsp;",
    "entre_calle":"&nbsp;",
    "y_calle":"&nbsp;",
    "calle_posterior":"&nbsp;",
    "codigo_postal":"&nbsp;",
    "lada":"&nbsp;",
    "telefono":"&nbsp;",
    "e_mail":"&nbsp;",
    "total_de_personal":"2",
    "personal_mujeres":"0",
    "personal_hombres":"2",
    "total_de_docentes":"2",
    "docentes_mujeres":"0",
    "docentes_hombres":"2",
    "total_de_alumnos":"38",
    "alumnos_mujeres":"20",
    "alumnos_hombres":"18",
    "total_de_grupos":"3",
    "aulas_existentes":"4",
    "aulas_en_uso":"4",
    "laboratorios":"1",
    "talleres":"0",
    "computadoras_en_operacion":"0",
    "computadoras_en_operacion_con_internet":"0",
    "computadoras_en_operacion_uso_educativo":"0",
    "altitud_msnm":"0598",
    "longitud":"-103.356569",
    "latitud":"18.510486",
    "longitud_gms":"-103:21:23.649",
    "latitud_gms":"18:30:37.751"
}
