{
    "periodo":"2015-2016",
    "tipo_educativo":"EDUCACI&#211;N B&#193;SICA",
    "nivel_educativo":"SECUNDARIA",
    "servicio_educativo":"TELESECUNDARIA",
    "clave_entidad":"16",
    "entidad":"MICHOAC&#193;N DE OCAMPO",
    "clave_mun_del":"035",
    "municipio":"LA HUACANA",
    "clave_localidad":"0283",
    "localidad":"SAN MIGUEL SILAHUA (LA NOPALERA)",
    "clave":"16ETV0656S",
    "turno":"MATUTINO",
    "ambito":"RURAL",
    "centro_educativo":"JOSE MARIA MORELOS Y PAVON",
    "control":"P&#218;BLICO",
    "domicilio":"DOMICILIO CONOCIDO",
    "num_exterior":"SN",
    "entre_calle":"CALLE SIN NOMBRE",
    "y_calle":"CALLE SIN NOMBRE",
    "calle_posterior":"CALLE SIN NOMBRE",
    "codigo_postal":"61863",
    "lada":"01443",
    "telefono":"323 6119",
    "e_mail":"16etv0656s@telesecundarias.michoacan.gob",
    "total_de_personal":"7",
    "personal_mujeres":"3",
    "personal_hombres":"4",
    "total_de_docentes":"6",
    "docentes_mujeres":"2",
    "docentes_hombres":"4",
    "total_de_alumnos":"81",
    "alumnos_mujeres":"45",
    "alumnos_hombres":"36",
    "total_de_grupos":"6",
    "aulas_existentes":"6",
    "aulas_en_uso":"6",
    "laboratorios":"0",
    "talleres":"0",
    "computadoras_en_operacion":"0",
    "computadoras_en_operacion_con_internet":"0",
    "computadoras_en_operacion_uso_educativo":"0",
    "altitud_msnm":"0180",
    "longitud":"-101.822778",
    "latitud":"18.721667",
    "longitud_gms":"-101:49:22.001",
    "latitud_gms":"18:43:18.001"
}
