{
    "periodo":"&nbsp;",
    "tipo_educativo":"EDUCACI&#211;N MEDIA SUPERIOR",
    "nivel_educativo":"BACHILLERATO",
    "servicio_educativo":"BACHILLERATO GENERAL",
    "clave_entidad":"19",
    "entidad":"NUEVO LE&#211;N",
    "clave_mun_del":"001",
    "municipio":"ABASOLO",
    "clave_localidad":"0001",
    "localidad":"ABASOLO",
    "clave":"19XMS0006E",
    "turno":"VESPERTINO",
    "ambito":"URBANA",
    "centro_educativo":"EXTENSION DR. GONZALEZ (PLANTEL AGUALEGUAS)",
    "control":"P&#218;BLICO",
    "domicilio":"&nbsp;",
    "num_exterior":"&nbsp;",
    "entre_calle":"&nbsp;",
    "y_calle":"&nbsp;",
    "calle_posterior":"&nbsp;",
    "codigo_postal":"&nbsp;",
    "lada":"&nbsp;",
    "telefono":"&nbsp;",
    "e_mail":"&nbsp;",
    "total_de_personal":"26",
    "personal_mujeres":"9",
    "personal_hombres":"17",
    "total_de_docentes":"17",
    "docentes_mujeres":"4",
    "docentes_hombres":"13",
    "total_de_alumnos":"94",
    "alumnos_mujeres":"44",
    "alumnos_hombres":"50",
    "total_de_grupos":"3",
    "aulas_existentes":"10",
    "aulas_en_uso":"10",
    "laboratorios":"1",
    "talleres":"0",
    "computadoras_en_operacion":"37",
    "computadoras_en_operacion_con_internet":"37",
    "computadoras_en_operacion_uso_educativo":"27",
    "altitud_msnm":"0368",
    "longitud":"-99.946551",
    "latitud":"25.857434",
    "longitud_gms":"-99:56:47.584",
    "latitud_gms":"25:51:26.762"
}
