{
    "periodo":"2015-2016",
    "tipo_educativo":"EDUCACI&#211;N B&#193;SICA",
    "nivel_educativo":"PREESCOLAR",
    "servicio_educativo":"PREESCOLAR IND&#205;GENA",
    "clave_entidad":"20",
    "entidad":"OAXACA",
    "clave_mun_del":"407",
    "municipio":"SANTA MAR&#205;A CHIMALAPA",
    "clave_localidad":"0003",
    "localidad":"TIERRA BLANCA",
    "clave":"20DCC1779R",
    "turno":"MATUTINO",
    "ambito":"RURAL",
    "centro_educativo":"CUAUHTEMOC",
    "control":"P&#218;BLICO",
    "domicilio":"LAZARO CARDENAS",
    "num_exterior":"&nbsp;",
    "entre_calle":"16 DE SEPTIEMBRE",
    "y_calle":"OAXACA",
    "calle_posterior":"NINGUNO",
    "codigo_postal":"70360",
    "lada":"01994",
    "telefono":"&nbsp;",
    "e_mail":"&nbsp;",
    "total_de_personal":"1",
    "personal_mujeres":"1",
    "personal_hombres":"0",
    "total_de_docentes":"1",
    "docentes_mujeres":"1",
    "docentes_hombres":"0",
    "total_de_alumnos":"29",
    "alumnos_mujeres":"16",
    "alumnos_hombres":"13",
    "total_de_grupos":"1",
    "aulas_existentes":"1",
    "aulas_en_uso":"1",
    "laboratorios":"0",
    "talleres":"0",
    "computadoras_en_operacion":"0",
    "computadoras_en_operacion_con_internet":"0",
    "computadoras_en_operacion_uso_educativo":"0",
    "altitud_msnm":"0100",
    "longitud":"-94.887914",
    "latitud":"16.884106",
    "longitud_gms":"-94:53:16.489",
    "latitud_gms":"16:53:02.781"
}
