{
    "periodo":"2015-2016",
    "tipo_educativo":"EDUCACI&#211;N B&#193;SICA",
    "nivel_educativo":"SECUNDARIA",
    "servicio_educativo":"TELESECUNDARIA",
    "clave_entidad":"20",
    "entidad":"OAXACA",
    "clave_mun_del":"302",
    "municipio":"SAN PEDRO ATOYAC",
    "clave_localidad":"0001",
    "localidad":"SAN PEDRO ATOYAC",
    "clave":"20DTV0504A",
    "turno":"MATUTINO",
    "ambito":"URBANA",
    "centro_educativo":"TELESECUNDARIA",
    "control":"P&#218;BLICO",
    "domicilio":"ENTRADA PRINCIPAL",
    "num_exterior":"SN",
    "entre_calle":"NINGUNO",
    "y_calle":"NINGUNO",
    "calle_posterior":"NINGUNO",
    "codigo_postal":"71710",
    "lada":"01954",
    "telefono":"5433336",
    "e_mail":"&nbsp;",
    "total_de_personal":"20",
    "personal_mujeres":"10",
    "personal_hombres":"10",
    "total_de_docentes":"14",
    "docentes_mujeres":"6",
    "docentes_hombres":"8",
    "total_de_alumnos":"261",
    "alumnos_mujeres":"122",
    "alumnos_hombres":"139",
    "total_de_grupos":"14",
    "aulas_existentes":"14",
    "aulas_en_uso":"14",
    "laboratorios":"0",
    "talleres":"0",
    "computadoras_en_operacion":"0",
    "computadoras_en_operacion_con_internet":"0",
    "computadoras_en_operacion_uso_educativo":"0",
    "altitud_msnm":"0239",
    "longitud":"-97.986519",
    "latitud":"16.489171",
    "longitud_gms":"-97:59:11.468",
    "latitud_gms":"16:29:21.016"
}
