{
    "periodo":"2015-2016",
    "tipo_educativo":"EDUCACI&#211;N B&#193;SICA",
    "nivel_educativo":"SECUNDARIA",
    "servicio_educativo":"TELESECUNDARIA",
    "clave_entidad":"21",
    "entidad":"PUEBLA",
    "clave_mun_del":"179",
    "municipio":"TLACHICHUCA",
    "clave_localidad":"0024",
    "localidad":"SANTA MAR&#205;A EL ASERRADERO (PEONES ACASILLADOS)",
    "clave":"21ETV0955B",
    "turno":"MATUTINO",
    "ambito":"RURAL",
    "centro_educativo":"LUIS DONALDO COLOSIO MURRIETA",
    "control":"P&#218;BLICO",
    "domicilio":"MIGUEL HIDALGO",
    "num_exterior":"&nbsp;",
    "entre_calle":"NINGUNO",
    "y_calle":"MORELOS",
    "calle_posterior":"NINGUNO",
    "codigo_postal":"75059",
    "lada":"01245",
    "telefono":"&nbsp;",
    "e_mail":"salas0412@hotmail.com",
    "total_de_personal":"1",
    "personal_mujeres":"0",
    "personal_hombres":"1",
    "total_de_docentes":"1",
    "docentes_mujeres":"0",
    "docentes_hombres":"1",
    "total_de_alumnos":"41",
    "alumnos_mujeres":"17",
    "alumnos_hombres":"24",
    "total_de_grupos":"3",
    "aulas_existentes":"2",
    "aulas_en_uso":"1",
    "laboratorios":"0",
    "talleres":"0",
    "computadoras_en_operacion":"0",
    "computadoras_en_operacion_con_internet":"0",
    "computadoras_en_operacion_uso_educativo":"0",
    "altitud_msnm":"2825",
    "longitud":"-97.382248",
    "latitud":"19.069892",
    "longitud_gms":"-97:22:56.091",
    "latitud_gms":"19:04:11.611"
}
