{
    "periodo":"2015-2016",
    "tipo_educativo":"EDUCACI&#211;N ESPECIAL",
    "nivel_educativo":"CAM",
    "servicio_educativo":"CAM",
    "clave_entidad":"23",
    "entidad":"QUINTANA ROO",
    "clave_mun_del":"004",
    "municipio":"OTH&#211;N P. BLANCO",
    "clave_localidad":"0001",
    "localidad":"CHETUMAL",
    "clave":"23DML0025Z",
    "turno":"VESPERTINO",
    "ambito":"URBANA",
    "centro_educativo":"CENTRO DE ATENCION MULTIPLE",
    "control":"P&#218;BLICO",
    "domicilio":"CALLE CELUL",
    "num_exterior":"SN",
    "entre_calle":"CALLE 12 DE OCTUBRE",
    "y_calle":"CALLE 24 DE NOVIEMBRE",
    "calle_posterior":"CALLE RAMONAL",
    "codigo_postal":"77086",
    "lada":"01983",
    "telefono":"&nbsp;",
    "e_mail":"&nbsp;",
    "total_de_personal":"13",
    "personal_mujeres":"10",
    "personal_hombres":"3",
    "total_de_docentes":"6",
    "docentes_mujeres":"5",
    "docentes_hombres":"1",
    "total_de_alumnos":"49",
    "alumnos_mujeres":"23",
    "alumnos_hombres":"26",
    "total_de_grupos":"6",
    "aulas_existentes":"7",
    "aulas_en_uso":"6",
    "laboratorios":"0",
    "talleres":"0",
    "computadoras_en_operacion":"0",
    "computadoras_en_operacion_con_internet":"0",
    "computadoras_en_operacion_uso_educativo":"0",
    "altitud_msnm":"0002",
    "longitud":"-88.297899",
    "latitud":"18.493889",
    "longitud_gms":"-88:17:52.436",
    "latitud_gms":"18:29:38.002"
}
