{
    "periodo":"&nbsp;",
    "tipo_educativo":"EDUCACI&#211;N MEDIA SUPERIOR",
    "nivel_educativo":"BACHILLERATO",
    "servicio_educativo":"PROFESIONAL T&#201;CNICO  B",
    "clave_entidad":"23",
    "entidad":"QUINTANA ROO",
    "clave_mun_del":"008",
    "municipio":"SOLIDARIDAD",
    "clave_localidad":"0001",
    "localidad":"PLAYA DEL CARMEN",
    "clave":"23DPT0007P",
    "turno":"MATUTINO",
    "ambito":"URBANA",
    "centro_educativo":"PLANTEL CONALEP 297. PLAYA DEL CARMEN",
    "control":"P&#218;BLICO",
    "domicilio":"&nbsp;",
    "num_exterior":"&nbsp;",
    "entre_calle":"&nbsp;",
    "y_calle":"&nbsp;",
    "calle_posterior":"&nbsp;",
    "codigo_postal":"&nbsp;",
    "lada":"&nbsp;",
    "telefono":"&nbsp;",
    "e_mail":"&nbsp;",
    "total_de_personal":"51",
    "personal_mujeres":"18",
    "personal_hombres":"33",
    "total_de_docentes":"26",
    "docentes_mujeres":"9",
    "docentes_hombres":"17",
    "total_de_alumnos":"348",
    "alumnos_mujeres":"194",
    "alumnos_hombres":"154",
    "total_de_grupos":"8",
    "aulas_existentes":"8",
    "aulas_en_uso":"8",
    "laboratorios":"2",
    "talleres":"3",
    "computadoras_en_operacion":"119",
    "computadoras_en_operacion_con_internet":"39",
    "computadoras_en_operacion_uso_educativo":"101",
    "altitud_msnm":"0008",
    "longitud":"-87.057707",
    "latitud":"20.685069",
    "longitud_gms":"-87:03:27.746",
    "latitud_gms":"20:41:06.247"
}
