{
    "periodo":"&nbsp;",
    "tipo_educativo":"EDUCACI&#211;N MEDIA SUPERIOR",
    "nivel_educativo":"BACHILLERATO",
    "servicio_educativo":"BACHILLERATO GENERAL",
    "clave_entidad":"24",
    "entidad":"SAN LUIS POTOS&#205;",
    "clave_mun_del":"028",
    "municipio":"SAN LUIS POTOS&#205;",
    "clave_localidad":"0001",
    "localidad":"SAN LUIS POTOS&#205;",
    "clave":"24PCB0003D",
    "turno":"MATUTINO",
    "ambito":"URBANA",
    "centro_educativo":"COLEGIO JUAN DE DIOS PEZA, A.C.",
    "control":"PRIVADO",
    "domicilio":"&nbsp;",
    "num_exterior":"&nbsp;",
    "entre_calle":"&nbsp;",
    "y_calle":"&nbsp;",
    "calle_posterior":"&nbsp;",
    "codigo_postal":"&nbsp;",
    "lada":"&nbsp;",
    "telefono":"&nbsp;",
    "e_mail":"&nbsp;",
    "total_de_personal":"24",
    "personal_mujeres":"13",
    "personal_hombres":"11",
    "total_de_docentes":"16",
    "docentes_mujeres":"7",
    "docentes_hombres":"9",
    "total_de_alumnos":"182",
    "alumnos_mujeres":"133",
    "alumnos_hombres":"49",
    "total_de_grupos":"7",
    "aulas_existentes":"7",
    "aulas_en_uso":"7",
    "laboratorios":"2",
    "talleres":"2",
    "computadoras_en_operacion":"185",
    "computadoras_en_operacion_con_internet":"185",
    "computadoras_en_operacion_uso_educativo":"160",
    "altitud_msnm":"1864",
    "longitud":"-100.985349",
    "latitud":"22.152172",
    "longitud_gms":"-100:59:07.257",
    "latitud_gms":"22:09:07.821"
}
