{
    "periodo":"&nbsp;",
    "tipo_educativo":"EDUCACI&#211;N B&#193;SICA",
    "nivel_educativo":"PRIMARIA",
    "servicio_educativo":"PRIMARIA GENERAL",
    "clave_entidad":"26",
    "entidad":"SONORA",
    "clave_mun_del":"036",
    "municipio":"MAGDALENA",
    "clave_localidad":"0001",
    "localidad":"MAGDALENA DE KINO",
    "clave":"26PPR0375X",
    "turno":"MATUTINO",
    "ambito":"URBANA",
    "centro_educativo":"COLEGIO VERDAD Y VIDA",
    "control":"PRIVADO",
    "domicilio":"CARRETERA INTERNACIONAL KILOMETRO 178.5",
    "num_exterior":"0",
    "entre_calle":"NINGUNO",
    "y_calle":"NINGUNO",
    "calle_posterior":"NINGUNO",
    "codigo_postal":"84160",
    "lada":"&nbsp;",
    "telefono":"3225101",
    "e_mail":"CVEMEXICO@GMAIL.COM; TODD.STOLLER",
    "total_de_personal":"0",
    "personal_mujeres":"0",
    "personal_hombres":"0",
    "total_de_docentes":"0",
    "docentes_mujeres":"0",
    "docentes_hombres":"0",
    "total_de_alumnos":"0",
    "alumnos_mujeres":"0",
    "alumnos_hombres":"0",
    "total_de_grupos":"0",
    "aulas_existentes":"0",
    "aulas_en_uso":"0",
    "laboratorios":"0",
    "talleres":"0",
    "computadoras_en_operacion":"0",
    "computadoras_en_operacion_con_internet":"0",
    "computadoras_en_operacion_uso_educativo":"0",
    "altitud_msnm":"0747",
    "longitud":"-110.969404",
    "latitud":"30.630356",
    "longitud_gms":"-110:58:09.856",
    "latitud_gms":"30:37:49.280"
}
