{
    "periodo":"2015-2016",
    "tipo_educativo":"EDUCACI&#211;N SUPERIOR",
    "nivel_educativo":"LICENCIATURA",
    "servicio_educativo":"LIC. UNIV. Y TEC.",
    "clave_entidad":"27",
    "entidad":"TABASCO",
    "clave_mun_del":"007",
    "municipio":"EMILIANO ZAPATA",
    "clave_localidad":"0001",
    "localidad":"EMILIANO ZAPATA",
    "clave":"27EUT0002A",
    "turno":"DISCONTINUO",
    "ambito":"URBANA",
    "centro_educativo":"UNIVERSIDAD TECNOL&#211;GICA DEL USUMACINTA",
    "control":"P&#218;BLICO",
    "domicilio":"LIBRAMIENTO GLORIETA EMILIANO ZAPATA-TENOSIQUE, COLONIA LAS LOMAS",
    "num_exterior":"&nbsp;",
    "entre_calle":"NINGUNO",
    "y_calle":"NINGUNO",
    "calle_posterior":"&nbsp;",
    "codigo_postal":"86997",
    "lada":"&nbsp;",
    "telefono":"3435690",
    "e_mail":"plaeva2000@yahoo.es",
    "total_de_personal":"75",
    "personal_mujeres":"39",
    "personal_hombres":"36",
    "total_de_docentes":"75",
    "docentes_mujeres":"39",
    "docentes_hombres":"36",
    "total_de_alumnos":"232",
    "alumnos_mujeres":"108",
    "alumnos_hombres":"124",
    "total_de_grupos":"0",
    "aulas_existentes":"24",
    "aulas_en_uso":"24",
    "laboratorios":"8",
    "talleres":"4",
    "computadoras_en_operacion":"0",
    "computadoras_en_operacion_con_internet":"0",
    "computadoras_en_operacion_uso_educativo":"0",
    "altitud_msnm":"0016",
    "longitud":"-91.773730",
    "latitud":"17.731340",
    "longitud_gms":"-91:46:25.428",
    "latitud_gms":"17:43:52.824"
}
