{
    "periodo":"2015-2016",
    "tipo_educativo":"EDUCACI&#211;N B&#193;SICA",
    "nivel_educativo":"PREESCOLAR",
    "servicio_educativo":"CENDI",
    "clave_entidad":"28",
    "entidad":"TAMAULIPAS",
    "clave_mun_del":"040",
    "municipio":"VALLE HERMOSO",
    "clave_localidad":"0001",
    "localidad":"VALLE HERMOSO",
    "clave":"28PDI0033M",
    "turno":"CONTINUO (7:00 A 22:00 HORAS)",
    "ambito":"URBANA",
    "centro_educativo":"CENTRO DE DESARROLLO INFANTIL DE VALLE HERMOSO",
    "control":"PRIVADO",
    "domicilio":"FRANCISCO I. MADERO",
    "num_exterior":"14",
    "entre_calle":"DOCTOR LUIS GARCIA LOPEZ (TERCERA)",
    "y_calle":"EDUARDO CHAVEZ (SEGUNDA)",
    "calle_posterior":"NINGUNO",
    "codigo_postal":"87500",
    "lada":"01894",
    "telefono":"8424830",
    "e_mail":"&nbsp;",
    "total_de_personal":"2",
    "personal_mujeres":"2",
    "personal_hombres":"0",
    "total_de_docentes":"2",
    "docentes_mujeres":"2",
    "docentes_hombres":"0",
    "total_de_alumnos":"31",
    "alumnos_mujeres":"16",
    "alumnos_hombres":"15",
    "total_de_grupos":"2",
    "aulas_existentes":"2",
    "aulas_en_uso":"2",
    "laboratorios":"0",
    "talleres":"0",
    "computadoras_en_operacion":"0",
    "computadoras_en_operacion_con_internet":"0",
    "computadoras_en_operacion_uso_educativo":"0",
    "altitud_msnm":"0016",
    "longitud":"-97.812114",
    "latitud":"25.669430",
    "longitud_gms":"-97:48:43.609",
    "latitud_gms":"25:40:09.948"
}
