{
    "periodo":"2015-2016",
    "tipo_educativo":"EDUCACI&#211;N B&#193;SICA",
    "nivel_educativo":"PREESCOLAR",
    "servicio_educativo":"PREESCOLAR GENERAL",
    "clave_entidad":"30",
    "entidad":"VERACRUZ DE IGNACIO DE LA LLAVE",
    "clave_mun_del":"155",
    "municipio":"TANTOYUCA",
    "clave_localidad":"0121",
    "localidad":"IXCANELCO",
    "clave":"30DJN1083G",
    "turno":"MATUTINO",
    "ambito":"RURAL",
    "centro_educativo":"ENRIQUE C. REBSAMEN",
    "control":"P&#218;BLICO",
    "domicilio":"5 DE MAYO",
    "num_exterior":"&nbsp;",
    "entre_calle":"IGNACIO CHARGOY",
    "y_calle":"LAZARO CARDENAS",
    "calle_posterior":"24 DE FEBRERO",
    "codigo_postal":"92100",
    "lada":"01789",
    "telefono":"&nbsp;",
    "e_mail":"&nbsp;",
    "total_de_personal":"4",
    "personal_mujeres":"3",
    "personal_hombres":"1",
    "total_de_docentes":"2",
    "docentes_mujeres":"2",
    "docentes_hombres":"0",
    "total_de_alumnos":"34",
    "alumnos_mujeres":"21",
    "alumnos_hombres":"13",
    "total_de_grupos":"3",
    "aulas_existentes":"3",
    "aulas_en_uso":"2",
    "laboratorios":"0",
    "talleres":"0",
    "computadoras_en_operacion":"0",
    "computadoras_en_operacion_con_internet":"0",
    "computadoras_en_operacion_uso_educativo":"0",
    "altitud_msnm":"0079",
    "longitud":"-98.192868",
    "latitud":"21.141154",
    "longitud_gms":"-98:11:34.326",
    "latitud_gms":"21:08:28.155"
}
