{
    "periodo":"2015-2016",
    "tipo_educativo":"EDUCACI&#211;N B&#193;SICA",
    "nivel_educativo":"PREESCOLAR",
    "servicio_educativo":"PREESCOLAR GENERAL",
    "clave_entidad":"30",
    "entidad":"VERACRUZ DE IGNACIO DE LA LLAVE",
    "clave_mun_del":"169",
    "municipio":"JOS&#201; AZUETA",
    "clave_localidad":"0071",
    "localidad":"TESECHOAC&#193;N",
    "clave":"30DJN1208Y",
    "turno":"MATUTINO",
    "ambito":"RURAL",
    "centro_educativo":"GABRIELA MISTRAL",
    "control":"P&#218;BLICO",
    "domicilio":"LA RIVERA",
    "num_exterior":"0",
    "entre_calle":"NI&#209;OS HEROES",
    "y_calle":"ISABEL DIAZ DE GUTIERREZ",
    "calle_posterior":"AVENIDA INGENIERO ANTONIO PAILLES BRIZUELA",
    "codigo_postal":"&nbsp;",
    "lada":"01283",
    "telefono":"&nbsp;",
    "e_mail":"&nbsp;",
    "total_de_personal":"3",
    "personal_mujeres":"3",
    "personal_hombres":"0",
    "total_de_docentes":"3",
    "docentes_mujeres":"3",
    "docentes_hombres":"0",
    "total_de_alumnos":"47",
    "alumnos_mujeres":"22",
    "alumnos_hombres":"25",
    "total_de_grupos":"3",
    "aulas_existentes":"3",
    "aulas_en_uso":"3",
    "laboratorios":"0",
    "talleres":"0",
    "computadoras_en_operacion":"0",
    "computadoras_en_operacion_con_internet":"0",
    "computadoras_en_operacion_uso_educativo":"0",
    "altitud_msnm":"0007",
    "longitud":"-95.652817",
    "latitud":"18.134044",
    "longitud_gms":"-95:39:10.141",
    "latitud_gms":"18:08:02.558"
}
