{
    "periodo":"2015-2016",
    "tipo_educativo":"EDUCACI&#211;N B&#193;SICA",
    "nivel_educativo":"PRIMARIA",
    "servicio_educativo":"PRIMARIA GENERAL",
    "clave_entidad":"30",
    "entidad":"VERACRUZ DE IGNACIO DE LA LLAVE",
    "clave_mun_del":"202",
    "municipio":"ZONTECOMATL&#193;N DE L&#211;PEZ Y FUENTES",
    "clave_localidad":"0011",
    "localidad":"LIMONTITLA",
    "clave":"30DPR1434K",
    "turno":"MATUTINO",
    "ambito":"RURAL",
    "centro_educativo":"MEXICO",
    "control":"P&#218;BLICO",
    "domicilio":"CARRETERA LIMON",
    "num_exterior":"&nbsp;",
    "entre_calle":"&nbsp;",
    "y_calle":"&nbsp;",
    "calle_posterior":"UNICO ACCESO DE LA COMUNIDAD",
    "codigo_postal":"92635",
    "lada":"&nbsp;",
    "telefono":"&nbsp;",
    "e_mail":"&nbsp;",
    "total_de_personal":"6",
    "personal_mujeres":"2",
    "personal_hombres":"4",
    "total_de_docentes":"6",
    "docentes_mujeres":"2",
    "docentes_hombres":"4",
    "total_de_alumnos":"78",
    "alumnos_mujeres":"38",
    "alumnos_hombres":"40",
    "total_de_grupos":"6",
    "aulas_existentes":"6",
    "aulas_en_uso":"6",
    "laboratorios":"0",
    "talleres":"0",
    "computadoras_en_operacion":"0",
    "computadoras_en_operacion_con_internet":"0",
    "computadoras_en_operacion_uso_educativo":"0",
    "altitud_msnm":"0451",
    "longitud":"-98.235127",
    "latitud":"20.736705",
    "longitud_gms":"-98:14:06.458",
    "latitud_gms":"20:44:12.137"
}
