{
    "periodo":"2015-2016",
    "tipo_educativo":"EDUCACI&#211;N B&#193;SICA",
    "nivel_educativo":"PRIMARIA",
    "servicio_educativo":"PRIMARIA GENERAL",
    "clave_entidad":"30",
    "entidad":"VERACRUZ DE IGNACIO DE LA LLAVE",
    "clave_mun_del":"040",
    "municipio":"COATZINTLA",
    "clave_localidad":"0001",
    "localidad":"COATZINTLA",
    "clave":"30DPR5542T",
    "turno":"VESPERTINO",
    "ambito":"URBANA",
    "centro_educativo":"EJERCITO MEXICANO",
    "control":"P&#218;BLICO",
    "domicilio":"LATAMAT SUR",
    "num_exterior":"4",
    "entre_calle":"COYAMETL",
    "y_calle":"DE LO QUIETO",
    "calle_posterior":"NINGUNO",
    "codigo_postal":"93164",
    "lada":"01782",
    "telefono":"&nbsp;",
    "e_mail":"&nbsp;",
    "total_de_personal":"10",
    "personal_mujeres":"3",
    "personal_hombres":"7",
    "total_de_docentes":"7",
    "docentes_mujeres":"2",
    "docentes_hombres":"5",
    "total_de_alumnos":"118",
    "alumnos_mujeres":"55",
    "alumnos_hombres":"63",
    "total_de_grupos":"7",
    "aulas_existentes":"12",
    "aulas_en_uso":"7",
    "laboratorios":"0",
    "talleres":"0",
    "computadoras_en_operacion":"0",
    "computadoras_en_operacion_con_internet":"0",
    "computadoras_en_operacion_uso_educativo":"0",
    "altitud_msnm":"0113",
    "longitud":"-97.450916",
    "latitud":"20.476932",
    "longitud_gms":"-97:27:03.299",
    "latitud_gms":"20:28:36.954"
}
