{
    "periodo":"2015-2016",
    "tipo_educativo":"EDUCACI&#211;N B&#193;SICA",
    "nivel_educativo":"PRIMARIA",
    "servicio_educativo":"PRIMARIA GENERAL",
    "clave_entidad":"30",
    "entidad":"VERACRUZ DE IGNACIO DE LA LLAVE",
    "clave_mun_del":"087",
    "municipio":"XALAPA",
    "clave_localidad":"0001",
    "localidad":"XALAPA-ENR&#205;QUEZ",
    "clave":"30DPR3481I",
    "turno":"MATUTINO",
    "ambito":"URBANA",
    "centro_educativo":"JUSTO SIERRA",
    "control":"P&#218;BLICO",
    "domicilio":"JALISCO",
    "num_exterior":"20",
    "entre_calle":"MORELIA",
    "y_calle":"CHILPANCINGO",
    "calle_posterior":"AGUASCALIENTES",
    "codigo_postal":"91130",
    "lada":"01228",
    "telefono":"8150475",
    "e_mail":"&nbsp;",
    "total_de_personal":"28",
    "personal_mujeres":"19",
    "personal_hombres":"9",
    "total_de_docentes":"18",
    "docentes_mujeres":"13",
    "docentes_hombres":"5",
    "total_de_alumnos":"385",
    "alumnos_mujeres":"183",
    "alumnos_hombres":"202",
    "total_de_grupos":"18",
    "aulas_existentes":"18",
    "aulas_en_uso":"18",
    "laboratorios":"0",
    "talleres":"0",
    "computadoras_en_operacion":"0",
    "computadoras_en_operacion_con_internet":"0",
    "computadoras_en_operacion_uso_educativo":"0",
    "altitud_msnm":"1392",
    "longitud":"-96.922838",
    "latitud":"19.550442",
    "longitud_gms":"-96:55:22.215",
    "latitud_gms":"19:33:01.590"
}
