{
    "periodo":"&nbsp;",
    "tipo_educativo":"EDUCACI&#211;N MEDIA SUPERIOR",
    "nivel_educativo":"BACHILLERATO",
    "servicio_educativo":"BACHILLERATO GENERAL",
    "clave_entidad":"30",
    "entidad":"VERACRUZ DE IGNACIO DE LA LLAVE",
    "clave_mun_del":"115",
    "municipio":"NOGALES",
    "clave_localidad":"0001",
    "localidad":"NOGALES",
    "clave":"30ECB0006F",
    "turno":"DISCONTINUO",
    "ambito":"URBANA",
    "centro_educativo":"COLEGIO DE BACHILLERES DEL ESTADO DE VERACRUZ PLANTEL 06 NOGALES HERIBERTO JARA CORONA",
    "control":"P&#218;BLICO",
    "domicilio":"&nbsp;",
    "num_exterior":"&nbsp;",
    "entre_calle":"&nbsp;",
    "y_calle":"&nbsp;",
    "calle_posterior":"&nbsp;",
    "codigo_postal":"&nbsp;",
    "lada":"&nbsp;",
    "telefono":"&nbsp;",
    "e_mail":"&nbsp;",
    "total_de_personal":"73",
    "personal_mujeres":"37",
    "personal_hombres":"36",
    "total_de_docentes":"47",
    "docentes_mujeres":"22",
    "docentes_hombres":"25",
    "total_de_alumnos":"1281",
    "alumnos_mujeres":"705",
    "alumnos_hombres":"576",
    "total_de_grupos":"30",
    "aulas_existentes":"13",
    "aulas_en_uso":"13",
    "laboratorios":"4",
    "talleres":"3",
    "computadoras_en_operacion":"44",
    "computadoras_en_operacion_con_internet":"44",
    "computadoras_en_operacion_uso_educativo":"30",
    "altitud_msnm":"1290",
    "longitud":"-97.157640",
    "latitud":"18.823846",
    "longitud_gms":"-97:09:27.503",
    "latitud_gms":"18:49:25.845"
}
