{
    "periodo":"2015-2016",
    "tipo_educativo":"EDUCACI&#211;N B&#193;SICA",
    "nivel_educativo":"SECUNDARIA",
    "servicio_educativo":"SECUNDARIA GENERAL",
    "clave_entidad":"32",
    "entidad":"ZACATECAS",
    "clave_mun_del":"020",
    "municipio":"JEREZ",
    "clave_localidad":"0001",
    "localidad":"JEREZ DE GARC&#205;A SALINAS",
    "clave":"32DES0045E",
    "turno":"MATUTINO",
    "ambito":"URBANA",
    "centro_educativo":"ARMANDO CRUZ PALOMINO",
    "control":"P&#218;BLICO",
    "domicilio":"JOSE INES",
    "num_exterior":"25",
    "entre_calle":"JOSE INES",
    "y_calle":"MARGARITA",
    "calle_posterior":"NINGUNO",
    "codigo_postal":"99440",
    "lada":"01494",
    "telefono":"9457592",
    "e_mail":"&nbsp;",
    "total_de_personal":"48",
    "personal_mujeres":"27",
    "personal_hombres":"21",
    "total_de_docentes":"32",
    "docentes_mujeres":"17",
    "docentes_hombres":"15",
    "total_de_alumnos":"400",
    "alumnos_mujeres":"201",
    "alumnos_hombres":"199",
    "total_de_grupos":"14",
    "aulas_existentes":"14",
    "aulas_en_uso":"14",
    "laboratorios":"0",
    "talleres":"0",
    "computadoras_en_operacion":"0",
    "computadoras_en_operacion_con_internet":"0",
    "computadoras_en_operacion_uso_educativo":"0",
    "altitud_msnm":"1999",
    "longitud":"-102.978298",
    "latitud":"22.657157",
    "longitud_gms":"-102:58:41.874",
    "latitud_gms":"22:39:25.766"
}
